key_bpm_renamer/__init__.py
key_bpm_renamer/renamer.py
key_bpm_renamer-0.1.1.dist-info/LICENSE
key_bpm_renamer-0.1.1.dist-info/METADATA
key_bpm_renamer-0.1.1.dist-info/WHEEL
key_bpm_renamer-0.1.1.dist-info/entry_points.txt
key_bpm_renamer-0.1.1.dist-info/top_level.txt
key_bpm_renamer-0.1.1.dist-info/RECORD
