Metadata-Version: 2.1
Name: key_bpm_renamer
Version: 0.1.1
Summary: A tool to rename audio files based on their key and BPM
Home-page: https://github.com/komly/key_bpm_renamer
Author: komly
Author-email: komly@yandex.ru
Classifier: Programming Language :: Python :: 3
Classifier: License :: OSI Approved :: MIT License
Classifier: Operating System :: OS Independent
License-File: LICENSE
Requires-Dist: eyed3
Requires-Dist: tinytag
Requires-Dist: pydub
Requires-Dist: essentia
